adsbee/__init__.py
adsbee/adsbee_ota.py
adsbee/at.py
adsbee-0.1.0.dist-info/METADATA
adsbee-0.1.0.dist-info/WHEEL
adsbee-0.1.0.dist-info/RECORD
