Metadata-Version: 2.1
Name: adsbee
Version: 0.1.0
Summary: Utility software functions for interacting with an ADSBee 1090 open-source ADSBee receiver.
Author: John McNelly
Author-email: jkailimcnelly@gmail.com
Requires-Python: >=3.10,<4.0
Classifier: Programming Language :: Python :: 3
Classifier: Programming Language :: Python :: 3.10
Classifier: Programming Language :: Python :: 3.11
Classifier: Programming Language :: Python :: 3.12
Requires-Dist: ecdsa (>=0.19.0,<0.20.0)
Requires-Dist: pyserial (>=3.5,<4.0)
Requires-Dist: websocket-client (>=1.8.0,<2.0.0)
